Workbook

Sheet Summary
A1: Orpheus v0.41 Increment Summary
A3: Working Pro package | B3: $20 / 90 min
A4: Target gross margin floor | B4: =Assumptions!B6 -> 0.7
A5: Max allowed TTS rate / 1M chars | B5: =Assumptions!B16 -> 30.917874
A6: Inworld current On-Demand GM | B6: =Provider_Scenarios!I4 -> 0.611125
A7: Inworld Creator-equivalent GM | B7: =Provider_Scenarios!I5 -> 0.611125
A8: Inworld Developer-equivalent GM | B8: =Provider_Scenarios!I6 -> 0.6577
A9: Inworld Growth-equivalent GM | B9: =Provider_Scenarios!I7 -> 0.704275
A10: Cartesia startup-equivalent GM | B10: =Provider_Scenarios!I10 -> 0.698686
A11: Recommended build path | B11: Inworld first + Cartesia benchmark; keep current-account and discounted-tier scenarios separate
A12: Working reading: Current Inworld live-smoke testing is on the $50 / 1M chars On-Demand / Creator rate. Preserve Developer ($40) and Growth ($30) scenarios, but do not treat $30 as current account truth. Pro $20 / 90 min remains conditional until the provider-rate scenario or realized usage clears the guardrail.
A13: Working reading: Current Inworld live-smoke testing is on the $50 / 1M chars On-Demand / Creator rate. Preserve Developer ($40) and Growth ($30) scenarios, but do not treat $30 as current account truth. Pro $20 / 90 min remains conditional until the provider-rate scenario or realized usage clears the guardrail.

Sheet Assumptions
A1: Inputs and Guardrails
A3: Input | B3: Value | C3: Notes | D3: Source / reference
A4: Pro monthly price | B4: 20 | C4: Current working plan anchor | D4: docs/prd/specs/pricing-packaging-and-unit-economics.md
A5: Pro included minutes | B5: 90 | C5: Conditional internal anchor | D5: docs/prd/specs/pricing-packaging-and-unit-economics.md
A6: Target gross margin floor | B6: 0.7 | C6: Before broader self-serve rollout | D6: docs/prd/specs/pricing-packaging-and-unit-economics.md
A7: Payment fee rate | B7: 0.03 | C7: Effective payment fee assumption | D7: docs/prd/specs/pricing-packaging-and-unit-economics.md
A8: Chars per audio minute | B8: 900 | C8: Average source characters per delivered audio minute; April 25 Spanish live smoke observed about 901 chars/min | D8: docs/prd/specs/pricing-packaging-and-unit-economics.md
A9: Retry overhead factor | B9: 1.15 | C9: Retry, re-stitch, orchestration overhead | D9: docs/prd/specs/pricing-packaging-and-unit-economics.md
A10: STT cost / audio minute | B10: 0.016 | C10: Current Google STT planning default | D10: https://cloud.google.com/speech-to-text/pricing
A11: Alignment compute / audio minute | B11: 0.01 | C11: Forced alignment or extra compute allowance | D11: Internal planning input
A12: Storage & delivery / audio minute | B12: 0.002 | C12: Artifact storage and delivery allocation | D12: Internal planning input
A13: Non-TTS cost / completed minute | B13: =SUM(B10:B12) -> 0.028 | C13: STT + alignment compute + storage | D13: Formula
A14: Plan exposure guardrail | B14: =B4*(1-B6-B7) -> 5.4 | C14: Revenue left for full included exposure after fees and target GM | D14: Formula
A15: Max total variable cost / minute | B15: =B14/B5 -> 0.06 | C15: Guardrail divided by included minutes | D15: Formula
A16: Max allowed TTS rate / 1M chars | B16: =((B15-B13)/B9)*(1000000/B8) -> 30.917874 | C16: Upper bound for Pro $20 / 90 min under current assumptions; compare provider scenarios against this value | D16: Formula

Sheet Provider_Scenarios
A1: Provider Cost Scenarios for Pro Guardrail
A3: Provider | B3: Scenario | C3: Public monthly plan price | D3: Included chars / credits | E3: Effective TTS rate / 1M chars | F3: TTS cost / completed min | G3: Full variable cost / completed min | H3: Full exposure cost @ Pro mins | I3: GM after fees @ Pro | J3: Status vs 70% floor | K3: Notes | L3: Source URL
A4: Inworld | B4: on_demand_current | C4: PAYG | E4: 50 | F4: =(E4/1000000*Assumptions!$B$8)*Assumptions!$B$9 -> 0.05175 | G4: =F4+Assumptions!$B$13 -> 0.07975 | H4: =G4*Assumptions!$B$5 -> 7.1775 | I4: =(Assumptions!$B$4-H4-Assumptions!$B$4*Assumptions!$B$7)/Assumptions!$B$4 -> 0.611125 | J4: =IF(I4>=Assumptions!$B$6,"PASS","FAIL") -> FAIL | K4: Current On-Demand account usage rate observed in April 2026; same TTS Max unit rate as Creator | L4: User-provided Inworld usage/pricing screenshots, 2026-04-25; https://inworld.ai/pricing
A5: Inworld | B5: creator_equivalent | C5: 25 | E5: 50 | F5: =(E5/1000000*Assumptions!$B$8)*Assumptions!$B$9 -> 0.05175 | G5: =F5+Assumptions!$B$13 -> 0.07975 | H5: =G5*Assumptions!$B$5 -> 7.1775 | I5: =(Assumptions!$B$4-H5-Assumptions!$B$4*Assumptions!$B$7)/Assumptions!$B$4 -> 0.611125 | J5: =IF(I5>=Assumptions!$B$6,"PASS","FAIL") -> FAIL | K5: Creator: $25 credits per month; TTS Max unit rate remains $50 / 1M chars | L5: User-provided Inworld pricing screenshot, 2026-04-25; https://inworld.ai/pricing
A6: Inworld | B6: developer_equivalent | C6: 300 | E6: 40 | F6: =(E6/1000000*Assumptions!$B$8)*Assumptions!$B$9 -> 0.0414 | G6: =F6+Assumptions!$B$13 -> 0.0694 | H6: =G6*Assumptions!$B$5 -> 6.246 | I6: =(Assumptions!$B$4-H6-Assumptions!$B$4*Assumptions!$B$7)/Assumptions!$B$4 -> 0.6577 | J6: =IF(I6>=Assumptions!$B$6,"PASS","FAIL") -> FAIL | K6: Developer: $300 credits per month with 20% off TTS and STT; TTS Max $40 / 1M chars | L6: User-provided Inworld pricing screenshot, 2026-04-25; https://inworld.ai/pricing
A7: Inworld | B7: growth_equivalent | C7: 1500 | E7: 30 | F7: =(E7/1000000*Assumptions!$B$8)*Assumptions!$B$9 -> 0.03105 | G7: =F7+Assumptions!$B$13 -> 0.05905 | H7: =G7*Assumptions!$B$5 -> 5.3145 | I7: =(Assumptions!$B$4-H7-Assumptions!$B$4*Assumptions!$B$7)/Assumptions!$B$4 -> 0.704275 | J7: =IF(I7>=Assumptions!$B$6,"PASS","FAIL") -> PASS | K7: Growth: $1,500 credits per month with 40% off TTS and STT; TTS Max $30 / 1M chars | L7: User-provided Inworld pricing screenshot, 2026-04-25; https://inworld.ai/pricing
A8: Inworld | B8: marketing_doc_equivalent | E8: 10 | F8: =(E8/1000000*Assumptions!$B$8)*Assumptions!$B$9 -> 0.01035 | G8: =F8+Assumptions!$B$13 -> 0.03835 | H8: =G8*Assumptions!$B$5 -> 3.4515 | I8: =(Assumptions!$B$4-H8-Assumptions!$B$4*Assumptions!$B$7)/Assumptions!$B$4 -> 0.797425 | J8: =IF(I8>=Assumptions!$B$6,"PASS","FAIL") -> PASS | K8: Public TTS API page states TTS-1.5 Max at $10 / 1M chars; not invoice-equivalent for current account | L8: https://inworld.ai/tts-api
A9: Cartesia | B9: scale_equivalent | C9: 239 | D9: 8000000 | E9: =C9/D9*1000000 -> 29.875 | F9: =(E9/1000000*Assumptions!$B$8)*Assumptions!$B$9 -> 0.030920625 | G9: =F9+Assumptions!$B$13 -> 0.058920625 | H9: =G9*Assumptions!$B$5 -> 5.3028562 | I9: =(Assumptions!$B$4-H9-Assumptions!$B$4*Assumptions!$B$7)/Assumptions!$B$4 -> 0.70485719 | J9: =IF(I9>=Assumptions!$B$6,"PASS","FAIL") -> PASS | K9: $239 / 8M credits; 1 credit per character | L9: https://cartesia.ai/pricing
A10: Cartesia | B10: startup_equivalent | C10: 39 | D10: 1250000 | E10: =C10/D10*1000000 -> 31.2 | F10: =(E10/1000000*Assumptions!$B$8)*Assumptions!$B$9 -> 0.032292 | G10: =F10+Assumptions!$B$13 -> 0.060292 | H10: =G10*Assumptions!$B$5 -> 5.42628 | I10: =(Assumptions!$B$4-H10-Assumptions!$B$4*Assumptions!$B$7)/Assumptions!$B$4 -> 0.698686 | J10: =IF(I10>=Assumptions!$B$6,"PASS","FAIL") -> FAIL | K10: $39 / 1.25M credits; 1 credit per character | L10: https://cartesia.ai/pricing
A11: Cartesia | B11: pro_equivalent | C11: 4 | D11: 100000 | E11: =C11/D11*1000000 -> 40 | F11: =(E11/1000000*Assumptions!$B$8)*Assumptions!$B$9 -> 0.0414 | G11: =F11+Assumptions!$B$13 -> 0.0694 | H11: =G11*Assumptions!$B$5 -> 6.246 | I11: =(Assumptions!$B$4-H11-Assumptions!$B$4*Assumptions!$B$7)/Assumptions!$B$4 -> 0.6577 | J11: =IF(I11>=Assumptions!$B$6,"PASS","FAIL") -> FAIL | K11: $4 / 100K credits; 1 credit per character | L11: https://cartesia.ai/pricing

Sheet Market_Benchmark
A1: Public Market Benchmarks
A3: Company | B3: Offer / plan | C3: Public price | D3: Included usage signal | E3: Long-form signal | F3: Timing / subtitle signal | G3: Strategic read | H3: Source URL
A4: ElevenLabs | B4: Starter | C4: $6/mo | D4: ~30 UI TTS min | E4: Studio access; 20 Studio projects | F4: Timing API available | G4: Broad self-serve entry; not a moat target | H4: https://elevenlabs.io/pricing
A5: ElevenLabs | B5: Creator | C5: $11/mo | D5: ~121 UI TTS min | E5: Long-form public self-serve path | F5: Timing API + STT + alignment stack | G5: Primary public benchmark for Orpheus workflow value | H5: https://elevenlabs.io/pricing
A6: ElevenLabs | B6: Pro | C6: $99/mo | D6: ~600 UI TTS min | E6: Higher-end self-serve package | F6: Broader quality / API export bundle | G6: Shows broad long-form category is already occupied | H6: https://elevenlabs.io/pricing
A7: ElevenLabs | B7: Studio limits | C7: n/a | D7: Up to 500 chapters / 400 paragraphs / 5000 chars each | E7: Very large project envelope | F7: Character timing, STT, and forced alignment available | G7: Orpheus cannot lead with 'supports long text' | H7: https://help.elevenlabs.io/hc/en-us/articles/28622761381905-Are-there-any-limitations-to-the-size-of-a-project-in-Studio
A8: WellSaid | B8: Creative | C8: $55/mo/user | D8: ~72 audio hours / year | E8: Workflow-first voiceover plan | F8: No direct caption export at this level | G8: Shows premium workflow pricing can be much higher than low-end API math | H8: https://www.wellsaid.io/ai-voice-pricing
A9: WellSaid | B9: Business | C9: Contact / higher tier | D9: ~144 audio hours / year | E9: Team workflow plan | F9: Includes SRT and VTT export | G9: Caption convenience can be a paid differentiator | H9: https://www.wellsaid.io/ai-voice-pricing
A10: Murf | B10: API PAYG | C10: $0.03 / 1000 chars | D10: PAYG | E10: Commodity API pressure | F10: No strong public subtitle story in this surfaced set | G10: Useful low-cost API reference, weaker wedge match | H10: https://help.murf.ai/murf-api-plans-and-limits
A11: Murf | B11: Falcon | C11: $0.01 / min | D11: API model reference | E11: Fast low-latency voice path | F11: n/a | G11: Good reminder that cheap API pricing exists in pockets | H11: https://murf.ai/text-to-speech
A12: Raphael | B12: Free / Premium / Ultimate | C12: Free / hidden paid prices | D12: 10 credits/day + unlimited slow basic / 2000 / 5000 credits | E12: Not audio | F12: n/a | G12: Borrow the low-friction funnel and tier clarity, not unlimited-free economics | H12: https://raphael.app/pricing
